jax_sysid/__init__.py
jax_sysid/models.py
jax_sysid/utils.py
jax_sysid-1.0.11.dist-info/licenses/LICENSE.txt
jax_sysid-1.0.11.dist-info/METADATA
jax_sysid-1.0.11.dist-info/WHEEL
jax_sysid-1.0.11.dist-info/top_level.txt
jax_sysid-1.0.11.dist-info/RECORD
