Metadata-Version: 2.4
Name: jax-sysid
Version: 1.0.11
Summary: A Python package for linear and nonlinear system identification and nonlinear regression using Jax.
Author-email: Alberto Bemporad <alberto.bemporad@imtlucca.it>
Project-URL: homepage, https://github.com/bemporad/jax-sysid
Keywords: system identification,subspace identification,nonlinear regression
Classifier: Programming Language :: Python :: 3
Classifier: License :: OSI Approved :: Apache Software License
Classifier: Operating System :: OS Independent
Requires-Python: <3.13,>=3.9
License-File: LICENSE.txt
Requires-Dist: numpy
Requires-Dist: scipy<=1.14.1
Requires-Dist: jax<=0.4.31
Requires-Dist: jaxopt
Requires-Dist: flax<=0.10.4
Requires-Dist: tqdm
Requires-Dist: matplotlib
Requires-Dist: joblib
Requires-Dist: equinox<=0.11.10
Requires-Dist: diffrax<=0.6.1
Dynamic: license-file
